mariadb_binlog_indexer/__init__.py
mariadb_binlog_indexer/indexer.py
mariadb_binlog_indexer/lib/indexer
mariadb_binlog_indexer-0.0.19.dist-info/METADATA
mariadb_binlog_indexer-0.0.19.dist-info/WHEEL
mariadb_binlog_indexer-0.0.19.dist-info/top_level.txt
mariadb_binlog_indexer-0.0.19.dist-info/RECORD
