Metadata-Version: 2.1
Name: mariadb_binlog_indexer
Version: 0.0.19
Summary: MariaDB Binlog Indexer for Faster Querying
Author-email: Frappe Cloud <cloud@frappe.io>
License: MIT
Classifier: Programming Language :: Python :: 3
Classifier: License :: OSI Approved :: MIT License
Classifier: Operating System :: POSIX :: Linux
Requires-Python: >=3.7
Requires-Dist: duckdb==1.2.2
